wrkmon/__init__.py
wrkmon/__main__.py
wrkmon/app.py
wrkmon/cli.py
wrkmon/core/__init__.py
wrkmon/core/cache.py
wrkmon/core/player.py
wrkmon/core/queue.py
wrkmon/core/youtube.py
wrkmon/data/__init__.py
wrkmon/data/database.py
wrkmon/data/migrations.py
wrkmon/data/models.py
wrkmon/ui/__init__.py
wrkmon/ui/components.py
wrkmon/ui/messages.py
wrkmon/ui/theme.py
wrkmon/ui/screens/__init__.py
wrkmon/ui/screens/history.py
wrkmon/ui/screens/player.py
wrkmon/ui/screens/playlist.py
wrkmon/ui/screens/search.py
wrkmon/ui/views/__init__.py
wrkmon/ui/views/history.py
wrkmon/ui/views/playlists.py
wrkmon/ui/views/queue.py
wrkmon/ui/views/search.py
wrkmon/ui/widgets/__init__.py
wrkmon/ui/widgets/header.py
wrkmon/ui/widgets/player_bar.py
wrkmon/ui/widgets/result_item.py
wrkmon/utils/__init__.py
wrkmon/utils/config.py
wrkmon/utils/mpv_installer.py
wrkmon/utils/stealth.py
wrkmon-1.0.1.dist-info/licenses/LICENSE
wrkmon-1.0.1.dist-info/METADATA
wrkmon-1.0.1.dist-info/WHEEL
wrkmon-1.0.1.dist-info/entry_points.txt
wrkmon-1.0.1.dist-info/top_level.txt
wrkmon-1.0.1.dist-info/RECORD
