Metadata-Version: 2.4
Name: wrkmon
Version: 1.0.1
Summary: Stealth TUI YouTube audio player - stream music while looking productive
Author-email: Umar Khan Yousafzai <umerfarooqkhan325@gmail.com>
License-Expression: MIT
Project-URL: Homepage, https://github.com/Umar-Khan-Yousafzai/Wrkmon-TUI-Youtube
Project-URL: Documentation, https://github.com/Umar-Khan-Yousafzai/Wrkmon-TUI-Youtube#readme
Project-URL: Repository, https://github.com/Umar-Khan-Yousafzai/Wrkmon-TUI-Youtube
Project-URL: Issues, https://github.com/Umar-Khan-Yousafzai/Wrkmon-TUI-Youtube/issues
Keywords: youtube,audio,player,tui,music,stealth,productivity,terminal
Classifier: Development Status :: 4 - Beta
Classifier: Environment :: Console
Classifier: Intended Audience :: Developers
Classifier: Intended Audience :: End Users/Desktop
Classifier: Operating System :: OS Independent
Classifier: Operating System :: Microsoft :: Windows
Classifier: Operating System :: POSIX :: Linux
Classifier: Operating System :: MacOS
Classifier: Programming Language :: Python :: 3
Classifier: Programming Language :: Python :: 3.10
Classifier: Programming Language :: Python :: 3.11
Classifier: Programming Language :: Python :: 3.12
Classifier: Topic :: Multimedia :: Sound/Audio :: Players
Requires-Python: >=3.10
License-File: LICENSE
Requires-Dist: textual>=0.50.0
Requires-Dist: typer>=0.9.0
Requires-Dist: yt-dlp>=2024.0.0
Requires-Dist: rich>=13.0.0
Requires-Dist: pywin32>=306; sys_platform == "win32"
Provides-Extra: dev
Requires-Dist: pytest>=8.0.0; extra == "dev"
Requires-Dist: ruff>=0.3.0; extra == "dev"
Dynamic: license-file
